whisper_streaming
