Metadata-Version: 2.2
Name: du_aio_whisper
Version: 0.0.2
Author: DYZ
Author-email: duyuchau@gmail.com
Maintainer: DYZ
Maintainer-email: duyuchau@gmail.com
License: MIT
Platform: all
Requires-Dist: openai
Dynamic: author
Dynamic: author-email
Dynamic: description-content-type
Dynamic: license
Dynamic: maintainer
Dynamic: maintainer-email
Dynamic: platform
Dynamic: requires-dist
